{
  "menu": [
    {
      "link": "about.html",
      "name": "О нас",
      "active": false
    },
    {
      "link": "portfolio.html",
      "name": "Портфолио",
      "active": true
    },
    {
      "link": "services.html",
      "name": "Услуги",
      "active": false
    },
    {
      "link": "video.html",
      "name": "Видео",
      "active": false
    },
    {
      "link": "contacts.html",
      "name": "Контакты",
      "active": false
    }
  ],
  "portfolioInfo": [
    {
      "title": "Наименование объекта",
      "text": "Проект планировки и застройки территории участков, расположенных по ул. Лесхозная в городе Чебоксары (форэскиз)",
      "mod": true
    },
    {
      "title": "Адрес",
      "text": "Чувашская Республика, г. Чебоксары, ул. Лесхозная"
    },
    {
      "title": "Стадия проекта",
      "text": "Форэскизный проект"
    },
    {
      "title": "Проектная организация",
      "text": "«Творческая мастерская архитекторов Токаревых»"
    },
    {
      "title": "Авторы проекта",
      "text": "Г. Токарева - руководитель авторского коллектива, О. Касимова, Р. Ахмадесв, Г. Камалова, А. Плеханова, Л. Султанова"
    },
    {
      "title": "Заказчик",
      "text": "АО «Чебоксарский речной порт»"
    },
    {
      "title": "Площадь участка",
      "text": "<b>1.06 га</b>",
      "mod": true
    },
    {
      "title": "Общая площадь зданий",
      "text": "<b>11 037 кв.м</b>",
      "mod": true
    }
  ],
  "portfolioImg": [
    {
      "img": "img/portfolio-1.jpg"
    },
    {
      "img": "img/project-2.jpg"
    },
    {
      "img": "img/project-3.jpg"
    },
    {
      "img": "img/project-4.jpg"
    },
    {
      "img": "img/project-5.jpg"
    },
    {
      "img": "img/project-5.jpg"
    }
  ]
}